{
  "playerid": "1199739",
  "name": "onweb",
  "hardcore": "0",
  "ascensions": "0",
  "path": "0",
  "sign": "None",
  "roninleft": "0",
  "casual": "0",
  "drunk": "0",
  "full": "0",
  "turnsplayed": "33780",
  "familiar": "1",
  "hp": "650",
  "mp": "1374",
  "meat": "29814411",
  "adventures": "200",
  "level": "29",
  "rawmuscle": "370608",
  "rawmysticality": "703849",
  "rawmoxie": "368723",
  "basemuscle": "608",
  "basemysticality": "838",
  "basemoxie": "607",
  "familiarexp": "0",
  "class": "4",
  "lastadv": {
    "id": "92",
    "name": "The Dire Warren",
    "link": "adventure.php?snarfblat=92",
    "container": "tutorial.php"
  },
  "title": "29",
  "pvpfights": "100",
  "maxhp": 650,
  "maxmp": 1374,
  "spleen": "0",
  "muscle": 616,
  "mysticality": 886,
  "moxie": 617,
  "famlevel": 1,
  "locked": false,
  "limitmode": 0,
  "daysthisrun": 7072,
  "equipment": {
    "hat": "3551",
    "shirt": "4898",
    "pants": "7198",
    "weapon": "115",
    "acc1": "2760",
    "acc2": "1485",
    "acc3": "6323",
    "container": "2080",
    "fakehands": 0,
    "cardsleeve": 0
  },
  "stickers": [
    "3512",
    "3512",
    "3512"
  ],
  "soulsauce": "100",
  "fury": 0,
  "pastathrall": 0,
  "pastathralllevel": 1,
  "folder_holder": [
    "00",
    "00",
    "00",
    "00",
    "00"
  ],
  "eleronkey": "ae244ecf60561f87b8bd2a013674ed3f",
  "flag_config": {
    "noinvpops": 0,
    "fastdecking": 0,
    "seenewaccts": 0,
    "modprotection": 0,
    "devskills": 0,
    "shortcharpane": 0,
    "lazyinventory": 0,
    "compactfights": 0,
    "poppvpsearch": 0,
    "questtracker": 0,
    "charpanepvp": 0,
    "australia": 0,
    "fffights": 0,
    "compactchar": 0,
    "noframesize": 0,
    "fullnesscounter": 0,
    "nodevdebug": 0,
    "noquestnudge": 0,
    "nocalendar": 0,
    "alwaystag": 0,
    "clanlogins": 0,
    "quickskills": 0,
    "hprestorers": 0,
    "hidejacko": 0,
    "anchorshelf": 0,
    "showoutfit": "1",
    "wowbar": 0,
    "swapfam": 0,
    "hidefamfilter": 0,
    "nonpixelimages": 0,
    "invimages": 0,
    "showhandedness": 0,
    "acclinks": 0,
    "invadvancedsort": 0,
    "powersort": 0,
    "autodiscard": 0,
    "unfamequip": 0,
    "invclose": 0,
    "sellstuffugly": 0,
    "oneclickcraft": 0,
    "dontscroll": 0,
    "multisume": 0,
    "threecolinv": 0,
    "profanity": 0,
    "tc_updatetitle": 0,
    "tc_alwayswho": 0,
    "tc_times": 0,
    "tc_combineallpublic": 0,
    "tc_eventsactive": 0,
    "tc_hidebadges": 0,
    "tc_colortabs": 0,
    "tc_modifierkey": 0,
    "tc_tabsonbottom": 0,
    "chatversion": 0,
    "chatsize": 0,
    "aabosses": 0,
    "compacteffects": 0,
    "slimhpmpdisplay": 0,
    "ignorezonewarnings": 0,
    "whichpenpal": 0,
    "compactmanuel": 0,
    "hideefarrows": 0,
    "questtrackertiny": 0,
    "questtrackerscroll": 0,
    "disablelovebugs": 0,
    "eternalmrj": 0,
    "boringdarts": 0,
    "nocyberview": 0,
    "autoattack": 0,
    "topmenu": 0
  },
  "recalledskills": 0,
  "freedralph": 0,
  "mcd": 0,
  "pwd": "e0fccc11de1309120fb15ccd25fe5b5f",
  "rollover": 1778556599,
  "turnsthisrun": 33780,
  "familiar_wellfed": 0,
  "elementalresistance": {
    "hot": 0,
    "cold": 0,
    "spooky": 0,
    "stench": 2,
    "sleaze": 0
  },
  "intrinsics": [],
  "familiarpic": "familiar1",
  "pathname": "",
  "coolitems": "",
  "daynumber": "8491",
  "paradoxicity": 0,
  "noncomforcers": [],
  "eternitycod": [
    0,
    0,
    0,
    0,
    0
  ],
  "effects": {
    "df3e73633630d0b3f3e96a910beff6ba": [
      "On Pins and Needles",
      "300",
      "pins",
      "item:5062",
      "836"
    ],
    "51a8a6e5102e2d238b8bf56a6bffc8da": [
      "Magically Delicious",
      "2225",
      "rrainbow",
      "",
      "2211"
    ],
    "626c8ef76cfc003c6ac2e65e9af5fd7a": [
      "Ode to Booze",
      "36525",
      "odetobooze",
      "skill:6014",
      "71"
    ]
  }
}